FCombLibrary.cpython-37m-darwin.so
FCombLibrary-1.0.9.dist-info/LICENSE
FCombLibrary-1.0.9.dist-info/METADATA
FCombLibrary-1.0.9.dist-info/WHEEL
FCombLibrary-1.0.9.dist-info/top_level.txt
FCombLibrary-1.0.9.dist-info/RECORD
