Metadata-Version: 1.0
Name: FCombLibrary
Version: 1.0.9
Summary: A tool for extracting frequency combination from a given list of frequencies.
Home-page: UNKNOWN
Author: Marco Müllner
Author-email: muellnermarco@gmail.com
License: UNKNOWN
Platform: UNKNOWN
